jfk_django_core/__init__.py
jfk_django_core/account_adapter.py
jfk_django_core/admin/__init__.py
jfk_django_core/apis/__init__.py
jfk_django_core/apis/base.py
jfk_django_core/apis/core.py
jfk_django_core/apis/jfk_authentication.py
jfk_django_core/apps.py
jfk_django_core/authentication.py
jfk_django_core/callhome.py
jfk_django_core/constants.py
jfk_django_core/management/__init__.py
jfk_django_core/management/commands/__init__.py
jfk_django_core/management/commands/callhome_version.py
jfk_django_core/migrations/0001_initial.py
jfk_django_core/migrations/__init__.py
jfk_django_core/models/__init__.py
jfk_django_core/models/core.py
jfk_django_core/models/healthcheck.py
jfk_django_core/serializers.py
jfk_django_core/settings.py
jfk_django_core/tasks/__init__.py
jfk_django_core/tasks/healtcheck_tasks.py
jfk_django_core/urls.py
jfk_django_core/utils.py
jfk_django_core/viewsets.py
jfk_django_core-1.6.0.dist-info/LICENSE
jfk_django_core-1.6.0.dist-info/METADATA
jfk_django_core-1.6.0.dist-info/WHEEL
jfk_django_core-1.6.0.dist-info/RECORD
