Metadata-Version: 2.3
Name: jfk-django-core
Version: 1.6.0
Summary: JFK-Django-Core
Author: JFK
Author-email: jakob.kaliwoda@gmail.com
Requires-Python: >=3.10,<4.0
Classifier: Programming Language :: Python :: 3
Classifier: Programming Language :: Python :: 3.10
Classifier: Programming Language :: Python :: 3.11
Classifier: Programming Language :: Python :: 3.12
Classifier: Programming Language :: Python :: 3.13
Requires-Dist: channels (==4.3.2)
Requires-Dist: channels-redis (==4.3.0)
Requires-Dist: django (==5.2.9)
Requires-Dist: django-allauth-ui (==1.8.1)
Requires-Dist: django-allauth[socialaccount] (==65.13.1)
Requires-Dist: django-celery-beat (==2.8.1)
Requires-Dist: django-celery-results (==2.6.0)
Requires-Dist: django-colorfield (==0.14.0)
Requires-Dist: django-cors-headers (==4.9.0)
Requires-Dist: django-extra-settings (==0.14.1)
Requires-Dist: django-filter (==25.2)
Requires-Dist: django-import-export (==4.3.14)
Requires-Dist: django-mass-edit (==3.5.0)
Requires-Dist: django-rest-knox (==5.0.2)
Requires-Dist: django-widget-tweaks (==1.5.0)
Requires-Dist: djangorestframework (==3.16.1)
Requires-Dist: drf-spectacular (==0.29.0)
Requires-Dist: drf-spectacular-sidecar (==2026.1.1)
Requires-Dist: gunicorn (==23.0.0)
Requires-Dist: psycopg2-binary (==2.9.11)
Requires-Dist: pytz (==2025.2)
Requires-Dist: redis (==7.1.0)
Requires-Dist: requests (==2.32.5)
Requires-Dist: slippers (==0.6.2)
Requires-Dist: uvicorn (==0.40.0)
Requires-Dist: websockets (==15.0.1)
Requires-Dist: whitenoise (==6.11.0)
